netan/__init__.py
netan/netan.py
netan-1.2.dist-info/licenses/LICENSE
netan-1.2.dist-info/METADATA
netan-1.2.dist-info/WHEEL
netan-1.2.dist-info/top_level.txt
netan-1.2.dist-info/RECORD
