Metadata-Version: 2.4
Name: netan
Version: 1.2
Summary: Network builder for multi-omics matrices (Rodin-compatible).
Author: Boris Minasenko
License: MIT
Project-URL: Homepage, https://github.com/BM-Boris/netan-lib
Requires-Python: >=3.10
License-File: LICENSE
Requires-Dist: rodin>=1.9.10
Requires-Dist: joblib>=1.2
Requires-Dist: tqdm>=4.65
Requires-Dist: anywidget
Dynamic: license-file
